[
  {
    "id": "0",
    "number": "الأبواب",
    "name": "",
    "badgeId": "0"
  },
  {
    "id": "1",
    "number": "1",
    "name": "باب الأسباط",
    "passed": true,
    "badgeId": "0"
  },
  {
    "id": "2",
    "number": "2",
    "name": "باب حطة",
    "badgeId": "0"
  },
  {
    "id": "3",
    "number": "3",
    "name": "باب العتم",
    "badgeId": "0"
  },
  {
    "id": "4",
    "number": "4",
    "name": "باب الغوانمة",
    "badgeId": "0"
  },
  {
    "id": "5",
    "number": "5",
    "name": "باب الناظر",
    "badgeId": "0"
  },
  {
    "id": "6",
    "number": "6",
    "name": "باب الحديد",
    "badgeId": "0"
  },
  {
    "id": "7",
    "number": "7",
    "name": "باب القطانين",
    "badgeId": "0"
  },
  {
    "id": "8",
    "number": "8",
    "name": "باب المطهرة",
    "badgeId": "0"
  },
  {
    "id": "9",
    "number": "9",
    "name": "باب السلسلة",
    "badgeId": "0"
  },
  {
    "id": "10",
    "number": "10",
    "name": "باب المغاربة",
    "badgeId": "0"
  },
  {
    "id": "11",
    "number": "11",
    "name": "باب الرحمة \n (مغلق)",
    "badgeId": "0"
  },
  {
    "id": "12",
    "number": "12",
    "name": "باب الجنائز \n (مغلق)",
    "badgeId": "0"
  },
  {
    "id": "13",
    "number": "13",
    "name": "الباب الثلاثي \n (مغلق)",
    "badgeId": "0"
  },
  {
    "id": "14",
    "number": "14",
    "name": "الباب المزدوج \n (مغلق)",
    "badgeId": "0"
  },
  {
    "id": "15",
    "number": "الأبواب",
    "name": "الأبواب",
    "badgeId": "0"
  },
  {
    "id": "16",
    "number": "المآذن",
    "name": "",
    "badgeId": "1"
  },
  {
    "id": "17",
    "number": "1",
    "name": "مئذنة باب المغاربة",
    "badgeId": "1"
  },
  {
    "id": "18",
    "number": "2",
    "name": "مئذنة باب السلسلة",
    "badgeId": "1"
  },
  {
    "id": "19",
    "number": "3",
    "name": "مئذنة باب الغوانمة",
    "badgeId": "1"
  },
  {
    "id": "20",
    "number": "4",
    "name": "مئذنة باب الأسباط",
    "badgeId": "1"
  },
  {
    "id": "21",
    "number": "المآذن",
    "name": "المآذن",
    "badgeId": "1"
  },
  {
    "id": "22",
    "number": "المساجد",
    "name": "",
    "badgeId": "2"
  },
  {
    "id": "23",
    "number": "1",
    "name": "المسجد القبلي",
    "badgeId": "2"
  },
  {
    "id": "24",
    "number": "2",
    "name": "المسجد القديم",
    "badgeId": "2"
  },
  {
    "id": "25",
    "number": "3",
    "name": "المصلى المرواني",
    "badgeId": "2"
  },
  {
    "id": "26",
    "number": "4",
    "name": "مسجد البراق",
    "badgeId": "2"
  },
  {
    "id": "27",
    "number": "5",
    "name": "مسجد المغاربة",
    "badgeId": "2"
  },
  {
    "id": "28",
    "number": "6",
    "name": "مسجد النساء",
    "badgeId": "2"
  },
  {
    "id": "29",
    "number": "المساجد",
    "name": "المساجد",
    "badgeId": "2"
  },
  {
    "id": "30",
    "number": "القباب",
    "name": "",
    "badgeId": "3"
  },
  {
    "id": "31",
    "number": "1",
    "name": "قبة الصخرة المشرفة",
    "badgeId": "3"
  },
  {
    "id": "32",
    "number": "2",
    "name": "قبة السلسلة",
    "badgeId": "3"
  },
  {
    "id": "33",
    "number": "3",
    "name": "قبة المعراج",
    "badgeId": "3"
  },
  {
    "id": "34",
    "number": "4",
    "name": "قبة موسى",
    "badgeId": "3"
  },
  {
    "id": "35",
    "number": "5",
    "name": "قبة النحوية",
    "badgeId": "3"
  },
  {
    "id": "36",
    "number": "6",
    "name": "قبة سليمان",
    "badgeId": "3"
  },
  {
    "id": "37",
    "number": "7",
    "name": "قبة الميزان",
    "badgeId": "3"
  },
  {
    "id": "38",
    "number": "8",
    "name": "قبة النبي",
    "badgeId": "3"
  },
  {
    "id": "39",
    "number": "9",
    "name": "قبة الأرواح",
    "badgeId": "3"
  },
  {
    "id": "40",
    "number": "10",
    "name": "قبة الخضر",
    "badgeId": "3"
  },
  {
    "id": "41",
    "number": "11",
    "name": "قبة يوسف آغا",
    "badgeId": "3"
  },
  {
    "id": "42",
    "number": "12",
    "name": "قبة يوسف",
    "badgeId": "3"
  },
  {
    "id": "43",
    "number": "13",
    "name": "قبة عشاق النبي",
    "badgeId": "3"
  },
  {
    "id": "44",
    "number": "14",
    "name": "قبة مهد عيسى",
    "badgeId": "3"
  },
  {
    "id": "45",
    "number": "15",
    "name": "قبة الشيخ الخليلي",
    "badgeId": "3"
  },
  {
    "id": "46",
    "number": "القباب",
    "name": "القباب",
    "badgeId": "3"
  },

  {
    "id": "101",
    "number": "قريبًا...",
    "name": "",
    "badgeId": "4"
  },

  {
    "id": "47",
    "number": "المدارس",
    "name": "",
    "badgeId": "4"
  },
  {
    "id": "48",
    "number": "1",
    "name": "مدرسة ورياض الأقصى الإسلامية",
    "badgeId": "4"
  },
  {
    "id": "49",
    "number": "2",
    "name": "ثانوية الأقصى الشرغية",
    "badgeId": "4"
  },
  {
    "id": "50",
    "number": "3",
    "name": "المدرسة الغادرية",
    "badgeId": "4"
  },
  {
    "id": "51",
    "number": "4",
    "name": "المدرسة الباسطية",
    "badgeId": "4"
  },
  {
    "id": "52",
    "number": "5",
    "name": "المدرسة الأمينية",
    "badgeId": "4"
  },
  {
    "id": "53",
    "number": "6",
    "name": "المدرسة الفارسية",
    "badgeId": "4"
  },
  {
    "id": "54",
    "number": "7",
    "name": "المدرسة الملكية",
    "badgeId": "4"
  },
  {
    "id": "55",
    "number": "8",
    "name": "المدرسة الأسعردية",
    "badgeId": "4"
  },
  {
    "id": "56",
    "number": "9",
    "name": "المدرسة المنجكية",
    "badgeId": "4"
  },
  {
    "id": "57",
    "number": "10",
    "name": "المدرسة العثمانية",
    "badgeId": "4"
  },
  {
    "id": "58",
    "number": "11",
    "name": "المدرسة الأشرفية",
    "badgeId": "4"
  },
  {
    "id": "59",
    "number": "12",
    "name": "المدرسة التكزية",
    "badgeId": "4"
  },
  {
    "id": "60",
    "number": "المدارس",
    "name": "المدارس",
    "badgeId": "4"
  },
  {
    "id": "61",
    "number": "الأروقة",
    "name": "",
    "badgeId": "5"
  },
  {
    "id": "62",
    "number": "1",
    "name": "الرواق الغربي",
    "badgeId": "5"
  },
  {
    "id": "63",
    "number": "2",
    "name": "الرواق الشمالي",
    "badgeId": "5"
  },
  {
    "id": "64",
    "number": "الأروقة",
    "name": "الأروقة",
    "badgeId": "5"
  },
  {
    "id": "65",
    "number": "البوائك",
    "name": "",
    "badgeId": "6"
  },
  {
    "id": "66",
    "number": "1",
    "name": "البائكة الشمالية",
    "badgeId": "6"
  },
  {
    "id": "67",
    "number": "2",
    "name": "البائكة الشمالية الغربية",
    "badgeId": "6"
  },
  {
    "id": "68",
    "number": "3",
    "name": "البائكة الغربية",
    "badgeId": "6"
  },
  {
    "id": "69",
    "number": "4",
    "name": "البائكة الجنوبية الغربية",
    "badgeId": "6"
  },
  {
  "id": "70",
  "number": "5",
  "name": "البائكة الجنوبية",
    "badgeId": "6"
  },
  {
    "id": "71",
    "number": "6",
    "name": "البائكة الجنوبية الشرقية",
    "badgeId": "6"
  },
  {
    "id": "72",
    "number": "7",
    "name": "البائكة الشرقية",
    "badgeId": "6"
  },
  {
    "id": "73",
    "number": "8",
    "name": "البائكة الشمالية الشرقية",
    "badgeId": "6"
  },
  {
    "id": "74",
    "number": "البوائك",
    "name": "البوائك",
    "badgeId": "6"
  },
  {
    "id": "75",
    "number": "الأسبلة",
    "name": "",
    "badgeId": "7"
  },
  {
    "id": "76",
    "number": "1",
    "name": "سبيل الكأس",
    "badgeId": "7"
  },
  {
    "id": "77",
    "number": "2",
    "name": "سبيل شعلان",
    "badgeId": "7"
  },
  {
    "id": "78",
    "number": "3",
    "name": "سبيل البصيري",
    "badgeId": "7"
  },
  {
    "id": "79",
    "number": "4",
    "name": "سبيل قايتباي",
    "badgeId": "7"
  },
  {
    "id": "80",
    "number": "5",
    "name": "سبيل قاسم باشا",
    "badgeId": "7"
  },
  {
    "id": "81",
    "number": "6",
    "name": "سبيل سليمان",
    "badgeId": "7"
  },
  {
    "id": "82",
    "number": "7",
    "name": "سبيل الشيخ بدير",
    "badgeId": "7"
  },
  {
    "id": "83",
    "number": "8",
    "name": "سبيل باب المغاربة",
    "badgeId": "7"
  },
  {
    "id": "84",
    "number": "9",
    "name": "سبيل حطة",
    "badgeId": "7"
  },
  {
    "id": "85",
    "number": "10",
    "name": "بركة الناريخ",
    "badgeId": "7"
  },
  {
    "id": "86",
    "number": "11",
    "name": "صهريج الملك عيسى",
    "badgeId": "7"
  },
  {
    "id": "87",
    "number": "12",
    "name": "سبيل منبر برهان الدين",
    "badgeId": "7"
  },
  {
    "id": "88",
    "number": "13",
    "name": "سبيل الزيتونة",
    "badgeId": "7"
  },
  {
    "id": "89",
    "number": "14",
    "name": "سبيل الرحمة",
    "badgeId": "7"
  },
  {
    "id": "90",
    "number": "الأسبلة",
    "name": "الأسبلة",
    "badgeId": "7"
  },
  {
    "id": "91",
    "number": "معالم أخرى",
    "name": "",
    "badgeId": "8"
  },
  {
    "id": "92",
    "number": "1",
    "name": "المحاريب (6)",
    "badgeId": "8"
  },
  {
    "id": "93",
    "number": "2",
    "name": "المصاطب (26)",
    "badgeId": "8"
  },
  {
    "id": "94",
    "number": "3",
    "name": "الآبار (25)",
    "badgeId": "8"
  },
  {
    "id": "95",
    "number": "أخرى",
    "name": "معالم أخرى",
    "badgeId": "8"
  },
  {
    "id": "96",
    "number": "أطماع واعتداءات",
    "name": "",
    "badgeId": "9"
  },
  {
    "id": "97",
    "number": "1",
    "name": "الهيكل المزعوم",
    "badgeId": "9"
  },
  {
    "id": "98",
    "number": "2",
    "name": "حائط البراق",
    "badgeId": "9"
  },
  {
    "id": "99",
    "number": "3",
    "name": "منبر نور الدين",
    "badgeId": "9"
  },
  {
    "id": "100",
    "number": "اعتداءات",
    "name": "أطماع واعتداءات",
    "badgeId": "9"
  }
]